flake8_flask/__init__.py
flake8_flask/constants.py
flake8_flask/flask_base_visitor.py
flake8_flask/jwt_token_checks.py
flake8_flask/main.py
flake8_flask/secure_set_cookies.py
flake8_flask/send_file_checks.py
flake8_flask/talisman_checks.py
flake8_flask/unescaped_template_file_extensions.py
flake8_flask/upsell_blueprint.py
flake8_flask/use_jsonify.py
flake8_flask-0.9.2.dist-info/entry_points.txt
flake8_flask-0.9.2.dist-info/WHEEL
flake8_flask-0.9.2.dist-info/METADATA
flake8_flask-0.9.2.dist-info/RECORD
